MANIFEST.in
README.rst
requirements.txt
setup.cfg
setup.py
djlicencias_sic/__init__.py
djlicencias_sic/config.py
djlicencias_sic/forms.py
djlicencias_sic/models.py
djlicencias_sic/storage.py
djlicencias_sic/urls.py
djlicencias_sic/views.py
djlicencias_sic.egg-info/PKG-INFO
djlicencias_sic.egg-info/SOURCES.txt
djlicencias_sic.egg-info/dependency_links.txt
djlicencias_sic.egg-info/requires.txt
djlicencias_sic.egg-info/top_level.txt
djlicencias_sic/__pycache__/__init__.cpython-37.pyc
djlicencias_sic/__pycache__/config.cpython-37.pyc
djlicencias_sic/__pycache__/forms.cpython-37.pyc
djlicencias_sic/__pycache__/models.cpython-37.pyc
djlicencias_sic/__pycache__/storage.cpython-37.pyc
djlicencias_sic/__pycache__/urls.cpython-37.pyc
djlicencias_sic/__pycache__/views.cpython-37.pyc
djlicencias_sic/templates/djlicencias_sic/base.html
djlicencias_sic/templates/djlicencias_sic/configuracion.html
djlicencias_sic/templates/djlicencias_sic/index.html
djlicencias_sic/templates/djlicencias_sic/preferencias.html